{
  "info": {
    "_postman_id": "bd4e3be6-041f-4d6f-8b3c-67e5c373cd87",
    "name": "SourceControl UI API Template",
    "schema": "https://schema.getpostman.com/json/collection/v2.1.0/collection.json"
  },
  "item": [
    {
      "name": "Template",
      "item": [
        {
          "name": "Получить шаблон для создания Pull Request",
          "request": {
            "description": "Возвращает шаблон описания для Pull Request в формате plain text",
            "url": {
              "path": [
                "repos",
                ":project_name",
                ":repo_name",
                "pulls",
                "template"
              ],
              "host": [
                "{{baseUrl}}"
              ],
              "query": [],
              "variable": [
                {
                  "disabled": false,
                  "type": "any",
                  "value": "<string>",
                  "key": "project_name",
                  "description": "(Required) Имя проекта"
                },
                {
                  "disabled": false,
                  "type": "any",
                  "value": "<string>",
                  "key": "repo_name",
                  "description": "(Required) Название репозитория"
                }
              ],
              "raw": "{{baseUrl}}/repos/:project_name/:repo_name/pulls/template"
            },
            "header": [
              {
                "key": "Accept",
                "value": "text/plain"
              }
            ],
            "method": "GET"
          },
          "response": [
            {
              "name": "Шаблон PR успешно получен",
              "originalRequest": {
                "url": {
                  "path": [
                    "repos",
                    ":project_name",
                    ":repo_name",
                    "pulls",
                    "template"
                  ],
                  "host": [
                    "{{baseUrl}}"
                  ],
                  "query": [],
                  "variable": [
                    {
                      "disabled": false,
                      "type": "any",
                      "value": "<string>",
                      "key": "project_name",
                      "description": "(Required) Имя проекта"
                    },
                    {
                      "disabled": false,
                      "type": "any",
                      "value": "<string>",
                      "key": "repo_name",
                      "description": "(Required) Название репозитория"
                    }
                  ],
                  "raw": "{{baseUrl}}/repos/:project_name/:repo_name/pulls/template"
                },
                "header": [
                  {
                    "key": "Accept",
                    "value": "text/plain"
                  }
                ],
                "method": "GET"
              },
              "status": "OK",
              "code": 200,
              "header": [
                {
                  "key": "Content-Type",
                  "value": "text/plain"
                }
              ],
              "body": "## Описание изменений\n\n## Связанные задачи\n\n## Тип изменений\n- [ ] Исправление бага\n- [ ] Новая функциональность\n- [ ] Изменение существующей функциональности\n- [ ] Документация\n\n## Тестирование\n\n## Чеклист\n- [ ] Код соответствует стилю проекта\n- [ ] Добавлены тесты\n- [ ] Документация обновлена\n\n## Дополнительная информация\n",
              "cookie": [],
              "_postman_previewlanguage": "text"
            },
            {
              "name": "Некорректный запрос",
              "originalRequest": {
                "url": {
                  "path": [
                    "repos",
                    ":project_name",
                    ":repo_name",
                    "pulls",
                    "template"
                  ],
                  "host": [
                    "{{baseUrl}}"
                  ],
                  "query": [],
                  "variable": [
                    {
                      "disabled": false,
                      "type": "any",
                      "value": "<string>",
                      "key": "project_name",
                      "description": "(Required) Имя проекта"
                    },
                    {
                      "disabled": false,
                      "type": "any",
                      "value": "<string>",
                      "key": "repo_name",
                      "description": "(Required) Название репозитория"
                    }
                  ],
                  "raw": "{{baseUrl}}/repos/:project_name/:repo_name/pulls/template"
                },
                "header": [
                  {
                    "key": "Accept",
                    "value": "application/json"
                  }
                ],
                "method": "GET"
              },
              "status": "Bad Request",
              "code": 400,
              "header": [
                {
                  "key": "Content-Type",
                  "value": "application/json"
                }
              ],
              "body": "{\n  \"type\": \"null\",\n  \"title\": \"Некорректный запрос\",\n  \"detail\": \"Проверьте корректность переданных данных\",\n  \"validation\": [\n    {\n      \"field\": \"name\",\n      \"error\": \"Ошибка в имени\"\n    },\n    {\n      \"field\": \"name\",\n      \"error\": \"Ошибка в имени\"\n    }\n  ]\n}",
              "cookie": [],
              "_postman_previewlanguage": "json"
            },
            {
              "name": "Требуется аутентификация",
              "originalRequest": {
                "url": {
                  "path": [
                    "repos",
                    ":project_name",
                    ":repo_name",
                    "pulls",
                    "template"
                  ],
                  "host": [
                    "{{baseUrl}}"
                  ],
                  "query": [],
                  "variable": [
                    {
                      "disabled": false,
                      "type": "any",
                      "value": "<string>",
                      "key": "project_name",
                      "description": "(Required) Имя проекта"
                    },
                    {
                      "disabled": false,
                      "type": "any",
                      "value": "<string>",
                      "key": "repo_name",
                      "description": "(Required) Название репозитория"
                    }
                  ],
                  "raw": "{{baseUrl}}/repos/:project_name/:repo_name/pulls/template"
                },
                "header": [
                  {
                    "key": "Accept",
                    "value": "application/json"
                  }
                ],
                "method": "GET"
              },
              "status": "Unauthorized",
              "code": 401,
              "header": [
                {
                  "key": "Content-Type",
                  "value": "application/json"
                }
              ],
              "body": "{\n  \"type\": \"null\",\n  \"title\": \"Некорректный запрос\",\n  \"detail\": \"Проверьте корректность переданных данных\",\n  \"validation\": [\n    {\n      \"field\": \"name\",\n      \"error\": \"Ошибка в имени\"\n    },\n    {\n      \"field\": \"name\",\n      \"error\": \"Ошибка в имени\"\n    }\n  ]\n}",
              "cookie": [],
              "_postman_previewlanguage": "json"
            },
            {
              "name": "Доступ запрещен",
              "originalRequest": {
                "url": {
                  "path": [
                    "repos",
                    ":project_name",
                    ":repo_name",
                    "pulls",
                    "template"
                  ],
                  "host": [
                    "{{baseUrl}}"
                  ],
                  "query": [],
                  "variable": [
                    {
                      "disabled": false,
                      "type": "any",
                      "value": "<string>",
                      "key": "project_name",
                      "description": "(Required) Имя проекта"
                    },
                    {
                      "disabled": false,
                      "type": "any",
                      "value": "<string>",
                      "key": "repo_name",
                      "description": "(Required) Название репозитория"
                    }
                  ],
                  "raw": "{{baseUrl}}/repos/:project_name/:repo_name/pulls/template"
                },
                "header": [
                  {
                    "key": "Accept",
                    "value": "application/json"
                  }
                ],
                "method": "GET"
              },
              "status": "Forbidden",
              "code": 403,
              "header": [
                {
                  "key": "Content-Type",
                  "value": "application/json"
                }
              ],
              "body": "{\n  \"type\": \"null\",\n  \"title\": \"Некорректный запрос\",\n  \"detail\": \"Проверьте корректность переданных данных\",\n  \"validation\": [\n    {\n      \"field\": \"name\",\n      \"error\": \"Ошибка в имени\"\n    },\n    {\n      \"field\": \"name\",\n      \"error\": \"Ошибка в имени\"\n    }\n  ]\n}",
              "cookie": [],
              "_postman_previewlanguage": "json"
            },
            {
              "name": "Ресурс не найден",
              "originalRequest": {
                "url": {
                  "path": [
                    "repos",
                    ":project_name",
                    ":repo_name",
                    "pulls",
                    "template"
                  ],
                  "host": [
                    "{{baseUrl}}"
                  ],
                  "query": [],
                  "variable": [
                    {
                      "disabled": false,
                      "type": "any",
                      "value": "<string>",
                      "key": "project_name",
                      "description": "(Required) Имя проекта"
                    },
                    {
                      "disabled": false,
                      "type": "any",
                      "value": "<string>",
                      "key": "repo_name",
                      "description": "(Required) Название репозитория"
                    }
                  ],
                  "raw": "{{baseUrl}}/repos/:project_name/:repo_name/pulls/template"
                },
                "header": [
                  {
                    "key": "Accept",
                    "value": "application/json"
                  }
                ],
                "method": "GET"
              },
              "status": "Not Found",
              "code": 404,
              "header": [
                {
                  "key": "Content-Type",
                  "value": "application/json"
                }
              ],
              "body": "{\n  \"type\": \"null\",\n  \"title\": \"Некорректный запрос\",\n  \"detail\": \"Проверьте корректность переданных данных\",\n  \"validation\": [\n    {\n      \"field\": \"name\",\n      \"error\": \"Ошибка в имени\"\n    },\n    {\n      \"field\": \"name\",\n      \"error\": \"Ошибка в имени\"\n    }\n  ]\n}",
              "cookie": [],
              "_postman_previewlanguage": "json"
            },
            {
              "name": "Ошибка сервера",
              "originalRequest": {
                "url": {
                  "path": [
                    "repos",
                    ":project_name",
                    ":repo_name",
                    "pulls",
                    "template"
                  ],
                  "host": [
                    "{{baseUrl}}"
                  ],
                  "query": [],
                  "variable": [
                    {
                      "disabled": false,
                      "type": "any",
                      "value": "<string>",
                      "key": "project_name",
                      "description": "(Required) Имя проекта"
                    },
                    {
                      "disabled": false,
                      "type": "any",
                      "value": "<string>",
                      "key": "repo_name",
                      "description": "(Required) Название репозитория"
                    }
                  ],
                  "raw": "{{baseUrl}}/repos/:project_name/:repo_name/pulls/template"
                },
                "header": [
                  {
                    "key": "Accept",
                    "value": "application/json"
                  }
                ],
                "method": "GET"
              },
              "status": "Internal Server Error",
              "code": 500,
              "header": [
                {
                  "key": "Content-Type",
                  "value": "application/json"
                }
              ],
              "body": "{\n  \"type\": \"null\",\n  \"title\": \"Некорректный запрос\",\n  \"detail\": \"Проверьте корректность переданных данных\",\n  \"validation\": [\n    {\n      \"field\": \"name\",\n      \"error\": \"Ошибка в имени\"\n    },\n    {\n      \"field\": \"name\",\n      \"error\": \"Ошибка в имени\"\n    }\n  ]\n}",
              "cookie": [],
              "_postman_previewlanguage": "json"
            }
          ]
        }
      ]
    }
  ],
  "auth": {
    "type": "basic",
    "basic": [
      {
        "key": "username",
        "value": "{{basicAuthUsername}}",
        "type": "string"
      },
      {
        "key": "password",
        "value": "{{basicAuthPassword}}",
        "type": "string"
      }
    ]
  }
}
